ai_tutors/__init__.py
ai_tutors/client.py
ai_tutors-1.0.2.dist-info/licenses/LICENSE
ai_tutors-1.0.2.dist-info/METADATA
ai_tutors-1.0.2.dist-info/WHEEL
ai_tutors-1.0.2.dist-info/top_level.txt
ai_tutors-1.0.2.dist-info/RECORD
