Metadata-Version: 2.4
Name: ai_tutors
Version: 1.0.2
Summary: A library for interacting with AI Tutors
Home-page: https://github.com/teaghan/ai-tutors
Author: Teaghan O'Briain
Author-email: obriaintb@gmail.com
License: MIT
Classifier: Development Status :: 4 - Beta
Classifier: Intended Audience :: Education
Classifier: Programming Language :: Python :: 3
Classifier: Programming Language :: Python :: 3.8
Classifier: Programming Language :: Python :: 3.9
Requires-Python: >=3.8
License-File: LICENSE
Requires-Dist: requests
Requires-Dist: ipython
Dynamic: author
Dynamic: author-email
Dynamic: classifier
Dynamic: description
Dynamic: description-content-type
Dynamic: home-page
Dynamic: license
Dynamic: license-file
Dynamic: requires-dist
Dynamic: requires-python
Dynamic: summary
